k_samplers/__init__.py
k_samplers/external.py
k_samplers/sampling.py
k_samplers/utils.py
k_samplers-1.0.0.dist-info/LICENSE
k_samplers-1.0.0.dist-info/METADATA
k_samplers-1.0.0.dist-info/WHEEL
k_samplers-1.0.0.dist-info/top_level.txt
k_samplers-1.0.0.dist-info/RECORD
